sanetinel/__init__.py
sanetinel/__main__.py
sanetinel/errors.py
sanetinel/impl.py
sanetinel/logging.py
sanetinel/math.py
sanetinel/sanetinel_experiment.py
sanetinel/thresholded_logging.py
sanetinel/types.py
sanetinel-0.1.9.dist-info/LICENSE
sanetinel-0.1.9.dist-info/METADATA
sanetinel-0.1.9.dist-info/WHEEL
sanetinel-0.1.9.dist-info/top_level.txt
sanetinel-0.1.9.dist-info/RECORD
