Metadata-Version: 2.1
Name: sanetinel
Version: 0.1.9
Summary: Algorithm monitoring by tracking variable value likelihoods.
Home-page: https://github.com/Sanetinel/python
Author: Simon Rovder
Author-email: simon.rovder@gmail.com
License: GPL
Platform: UNKNOWN
Classifier: Programming Language :: Python :: 3
Classifier: Operating System :: OS Independent
Requires-Python: >=3.5
Provides-Extra: plotting
Requires-Dist: matplotlib ; extra == 'plotting'
